<?xml version="1.0" encoding="UTF-8"?>
<objects serializationModel="Studio.02.02.00">
	<object class="AudioFile" id="{9bd58124-24bd-40d0-819f-866b2c4fbf93}">
		<property name="assetPath">
			<value>Temp/voice_sans.mp3</value>
		</property>
		<property name="frequencyInKHz">
			<value>44.0999985</value>
		</property>
		<property name="channelCount">
			<value>2</value>
		</property>
		<property name="length">
			<value>0.2089795918367347</value>
		</property>
		<relationship name="masterAssetFolder">
			<destination>{f2bd821e-def3-4680-abf2-1a35f19200a9}</destination>
		</relationship>
	</object>
</objects>
