<?xml version="1.0" encoding="UTF-8"?>
<objects serializationModel="Studio.02.02.00">
	<object class="ParameterPreset" id="{9290a6a0-10c7-489f-8e0f-20a224d9e6b0}">
		<property name="name">
			<value>trackVol</value>
		</property>
		<relationship name="folder">
			<destination>{5375acb7-cde6-4f64-9844-c25f50ee9ca9}</destination>
		</relationship>
		<relationship name="parameter">
			<destination>{8afdfc63-02de-4888-8422-0d827e209ad7}</destination>
		</relationship>
	</object>
	<object class="GameParameter" id="{8afdfc63-02de-4888-8422-0d827e209ad7}">
		<property name="initialValue">
			<value>0</value>
		</property>
	</object>
</objects>
